KEGGDecoder/.DS_Store
KEGGDecoder/.gitignore
KEGGDecoder/Decode_and_Expand.py
KEGGDecoder/KEGG_clustering.py
KEGGDecoder/KEGG_decoder.py
KEGGDecoder/KEGG_expander.py
KEGGDecoder/KOALA_definitions.txt
KEGGDecoder/MakeTanglegram.py
KEGGDecoder/Pfam_definitions.txt
KEGGDecoder/Plotly_viz.py
KEGGDecoder/README.md
KEGGDecoder/__init__.py
KEGGDecoder/Amphibactin/ABO2092homolog_ref.faa
KEGGDecoder/Amphibactin/ABO2093homolog_ref.faa
KEGGDecoder/Amphibactin/amphibactin.sfam.hmm
KEGGDecoder/Amphibactin/amphibactin2092_sfam_match.tblout
KEGGDecoder/Amphibactin/amphibactin2093_sfam_match.tblout
KEGGDecoder/DMSPLyase/.DS_Store
KEGGDecoder/DMSPLyase/14591.hmm
KEGGDecoder/DMSPLyase/25993.hmm
KEGGDecoder/DMSPLyase/274874.hmm
KEGGDecoder/DMSPLyase/94923.hmm
KEGGDecoder/DMSPLyase/Pelagibacter_ref_dddK.faa
KEGGDecoder/DMSPLyase/dmdA_37326.hmm
KEGGDecoder/DMSPSynthase/4254.hmm
KEGGDecoder/DMSPSynthase/curson_dmsp_synthase.faa
KEGGDecoder/DMSPSynthase/img_dmsp_synthase_dsyB.faa
KEGGDecoder/DMSPSynthase/ncbi_dmsp_synthase_dsyB.faa
KEGGDecoder/DesferrioxamineBiosynthesis/Streptomycetes_ref_pathway.faa
KEGGDecoder/DesferrioxamineBiosynthesis/ferrioxamine.sfam.hmm
KEGGDecoder/DesferrioxamineBiosynthesis/ferrioxamine_sfam_match.tblout
KEGGDecoder/HMM_Models/.DS_Store
KEGGDecoder/HMM_Models/14591.hmm
KEGGDecoder/HMM_Models/25993.hmm
KEGGDecoder/HMM_Models/274874.hmm
KEGGDecoder/HMM_Models/4254.hmm
KEGGDecoder/HMM_Models/94923.hmm
KEGGDecoder/HMM_Models/Ammonium_transp.hmm
KEGGDecoder/HMM_Models/AnfG_VnfG.hmm
KEGGDecoder/HMM_Models/Bac_rhodopsin.hmm
KEGGDecoder/HMM_Models/CbtB.hmm
KEGGDecoder/HMM_Models/Copper_HMA.hmm
KEGGDecoder/HMM_Models/DMSP_lyase.hmm
KEGGDecoder/HMM_Models/DsrD.hmm
KEGGDecoder/HMM_Models/Oxidored_nitro.hmm
KEGGDecoder/HMM_Models/ZupT.hmm
KEGGDecoder/HMM_Models/amphibactin.sfam.hmm
KEGGDecoder/HMM_Models/anfD_nitrogenase.hmm
KEGGDecoder/HMM_Models/anfG_nitrogenase.hmm
KEGGDecoder/HMM_Models/anfK_nitrogenase.hmm
KEGGDecoder/HMM_Models/blh_betacarotenemonox.hmm
KEGGDecoder-1.3.dist-info/entry_points.txt
KEGGDecoder-1.3.dist-info/LICENSE
KEGGDecoder-1.3.dist-info/WHEEL
KEGGDecoder-1.3.dist-info/METADATA
KEGGDecoder-1.3.dist-info/RECORD
