Metadata-Version: 2.1
Name: KEGGDecoder
Version: 1.3
Summary: Designed to parse through a blastKoala or ghostKoala output to determine
Home-page: https://github.com/bjtully/BioData/KEGGDecoder
License: UNKNOWN
Author: Benjamin Tully
Author-email: tully.bj@gmail.com
Classifier: License :: OSI Approved :: MIT License
Requires-Dist: matplotlib==3.0.3
Requires-Dist: seaborn==0.9.0
Requires-Dist: pandas==0.25.2
Requires-Dist: numpy==1.17.3
Requires-Dist: plotly==4.2.1
Requires-Dist: tanglegram==0.1.0
Requires-Dist: biopython==1.74
Requires-Dist: scipy==1.3.1
